<annotation><filename>frame_81.jpg</filename><size><height>482</height><width>640</width><depth>3</depth></size><object><name>Car</name><difficult>0</difficult><bndbox><xmin>273</xmin><ymin>79</ymin><xmax>358</xmax><ymax>188</ymax></bndbox></object><object><name>Person</name><difficult>0</difficult><bndbox><xmin>509</xmin><ymin>142</ymin><xmax>548</xmax><ymax>225</ymax></bndbox></object><object><name>Person</name><difficult>0</difficult><bndbox><xmin>384</xmin><ymin>23</ymin><xmax>414</xmax><ymax>82</ymax></bndbox></object><object><name>Car</name><difficult>0</difficult><bndbox><xmin>321</xmin><ymin>384</ymin><xmax>444</xmax><ymax>477</ymax></bndbox></object></annotation>